torch2trt/__init__.py
torch2trt/calibration.py
torch2trt/module_test.py
torch2trt/test.py
torch2trt/torch2trt.py
torch2trt/utils.py
torch2trt/converters/AdaptiveAvgPool2d.py
torch2trt/converters/BatchNorm1d.py
torch2trt/converters/BatchNorm2d.py
torch2trt/converters/Conv1d.py
torch2trt/converters/Conv2d.py
torch2trt/converters/ConvTranspose2d.py
torch2trt/converters/Identity.py
torch2trt/converters/Linear.py
torch2trt/converters/LogSoftmax.py
torch2trt/converters/ReLU.py
torch2trt/converters/ReLU6.py
torch2trt/converters/__init__.py
torch2trt/converters/activation.py
torch2trt/converters/adaptive_avg_pool2d.py
torch2trt/converters/adaptive_max_pool2d.py
torch2trt/converters/add.py
torch2trt/converters/avg_pool2d.py
torch2trt/converters/cat.py
torch2trt/converters/chunk.py
torch2trt/converters/clamp.py
torch2trt/converters/div.py
torch2trt/converters/dummy_converters.py
torch2trt/converters/getitem.py
torch2trt/converters/identity.py
torch2trt/converters/instance_norm.py
torch2trt/converters/max.py
torch2trt/converters/max_pool2d.py
torch2trt/converters/mean.py
torch2trt/converters/min.py
torch2trt/converters/mul.py
torch2trt/converters/normalize.py
torch2trt/converters/pad.py
torch2trt/converters/permute.py
torch2trt/converters/pow.py
torch2trt/converters/prelu.py
torch2trt/converters/prod.py
torch2trt/converters/relu.py
torch2trt/converters/relu6.py
torch2trt/converters/sigmoid.py
torch2trt/converters/softmax.py
torch2trt/converters/split.py
torch2trt/converters/sub.py
torch2trt/converters/sum.py
torch2trt/converters/tanh.py
torch2trt/converters/transpose.py
torch2trt/converters/unary.py
torch2trt/converters/view.py
torch2trt/converters/interpolate/__init__.py
torch2trt/converters/interpolate/interpolate.py
torch2trt/tests/__init__.py
torch2trt/tests/torchvision/__init__.py
torch2trt/tests/torchvision/classification.py
torch2trt/tests/torchvision/save_load.py
torch2trt/tests/torchvision/segmentation.py
torch2trt_unofficial-0.0.3.dist-info/LICENSE.md
torch2trt_unofficial-0.0.3.dist-info/METADATA
torch2trt_unofficial-0.0.3.dist-info/WHEEL
torch2trt_unofficial-0.0.3.dist-info/top_level.txt
torch2trt_unofficial-0.0.3.dist-info/RECORD
