Metadata-Version: 2.1
Name: torch2trt-unofficial
Version: 0.0.3
Summary: An easy to use PyTorch to TensorRT converter
Home-page: UNKNOWN
Author: UNKNOWN
Author-email: UNKNOWN
License: UNKNOWN
Platform: UNKNOWN
